{"is_source_file": true, "file_id": 14, "git_revision": "", "state": 1, "description": "", "external_files": [], "external_methods": [], "published": [], "classes": [], "methods": [], "calls": [], "search-terms": [], "ctags": [{"_type": "tag", "name": "MONTHS", "path": "/home/kavia/workspace/code-generation/simple-notes-app-304312-304321/frontend_react/src/utils/format.js", "pattern": "/^const MONTHS = [\"Jan\", \"Feb\", \"Mar\", \"Apr\", \"May\", \"Jun\", \"Jul\", \"Aug\", \"Sep\", \"Oct\", \"Nov\", \"De/", "language": "JavaScript", "kind": "constant"}, {"_type": "tag", "name": "formatUpdatedAt", "path": "/home/kavia/workspace/code-generation/simple-notes-app-304312-304321/frontend_react/src/utils/format.js", "pattern": "/^export function formatUpdatedAt(epochMs) {$/", "language": "JavaScript", "kind": "function", "signature": "(epochMs)"}, {"_type": "tag", "name": "snippet", "path": "/home/kavia/workspace/code-generation/simple-notes-app-304312-304321/frontend_react/src/utils/format.js", "pattern": "/^export function snippet(text, maxLen = 140) {$/", "language": "JavaScript", "kind": "function", "signature": "(text, maxLen = 140)"}], "format": "JavaScript", "hash": "1f16d195c58e403347ad94b0acd4fcfe", "format-version": 4, "code-base-name": "frontend_react", "filename": "frontend_react/src/utils/format.js", "knowledge_revision": 27}